{
	"id": "4584d972-a842-41fb-8b32-c419bbd20b35",
	"values": [
		{
			"key": "BaseURL",
			"value": "https://api.trello.com",
			"type": "default",
			"enabled": true
		},
		{
			"key": "token",
			"value": "ATTA373fc8f1d8b7688343fdc236c5b7b0eb9",
			"type": "default",
			"enabled": true
		},
		{
			"key": "key",
			"value": "e1ce1e",
			"type": "default",
			"enabled": true
		}
	],
	"name": "Globals",
	"_postman_variable_scope": "globals",
	"_postman_exported_at": "2023-01-19T10:08:16.161Z",
	"_postman_exported_using": "Postman/10.8.4-230116-1713"
}
